cjapy/__init__.py
cjapy/__version__.py
cjapy/cjapy.py
cjapy/config.py
cjapy/configs.py
cjapy/connector.py
cjapy/projects.py
cjapy/requestCreator.py
cjapy/token_provider.py
cjapy/workspace.py
cjapy-0.2.4.post3.dist-info/licenses/LICENSE
cjapy-0.2.4.post3.dist-info/METADATA
cjapy-0.2.4.post3.dist-info/WHEEL
cjapy-0.2.4.post3.dist-info/top_level.txt
cjapy-0.2.4.post3.dist-info/RECORD
