Metadata-Version: 2.4
Name: cjapy
Version: 0.2.4.post3
Summary: Adobe Customer Journey Analytics (CJA) wrapper
Home-page: https://github.com/pitchmuc/cjapy
Author: Julien Piccini
Author-email: Julien Piccini <piccini.julien@gmail.com>
License: Apache License 2.0
Project-URL: homepage, https://github.com/pitchmuc/cjapy
Project-URL: changelog, https://github.com/pitchmuc/cjapy/blob/master/docs/releases.md
Keywords: adobe,analytics,API,python
Classifier: Intended Audience :: Developers
Classifier: License :: OSI Approved :: GNU General Public License v3 (GPLv3)
Classifier: Operating System :: OS Independent
Classifier: Programming Language :: Python
Classifier: Topic :: Scientific/Engineering :: Information Analysis
Classifier: Programming Language :: Python :: 3.6
Classifier: Programming Language :: Python :: 3.7
Classifier: Programming Language :: Python :: 3.8
Classifier: Programming Language :: Python :: 3.9
Classifier: Development Status :: 4 - Beta
Requires-Python: >=3.6
License-File: LICENSE
Requires-Dist: pandas
Requires-Dist: pathlib2
Requires-Dist: pathlib
Requires-Dist: requests
Requires-Dist: PyJWT
Requires-Dist: PyJWT[crypto]
Requires-Dist: pytest
Provides-Extra: dynamic
Requires-Dist: version; extra == "dynamic"
Dynamic: author
Dynamic: home-page
Dynamic: license-file
Dynamic: requires-python
